logging_exceptions.py
logging_exceptions-0.1.8.dist-info/DESCRIPTION.rst
logging_exceptions-0.1.8.dist-info/METADATA
logging_exceptions-0.1.8.dist-info/RECORD
logging_exceptions-0.1.8.dist-info/WHEEL
logging_exceptions-0.1.8.dist-info/metadata.json
logging_exceptions-0.1.8.dist-info/top_level.txt
