Metadata-Version: 2.0
Name: logging-exceptions
Version: 0.1.8
Summary: Self-logging exceptions: Attach log messages to exceptions and output them conditionally.
Home-page: https://github.com/Bernhard10/logging_exceptions
Author: Bernhard C. Thiel
Author-email: thiel@tbi.univie.ac.at
License: MIT
Keywords: logging exceptions
Platform: UNKNOWN
Classifier: Development Status :: 4 - Beta
Classifier: Intended Audience :: Developers
Classifier: Programming Language :: Python :: 2
Classifier: Programming Language :: Python :: 2.7
Classifier: Programming Language :: Python :: 3
Classifier: Programming Language :: Python :: 3.5
